{
  "manifest": {
    "apis": {
      "custom": {
        "endpoint": {
          "uri": "arn:aws:lambda:us-east-1:552719073693:function:002f4eb0-0f05-45a7-af49-f0b4e7fb1a11:Release_0"
        },
        "interfaces": [
          {
            "type": "RENDER_TEMPLATE",
            "minimumTemplateVersion": "1.0"
          }
        ]
      }
    },
    "permissions": [
      {
        "name": "alexa::profile:given_name:read"
      },
      {
        "name": "payments:autopay_consent"
      },
      {
        "name": "alexa::person_id:read"
      }
    ],
    "publishingInformation": {
      "locales": {
        "en-US": {
          "name": "Boba Maker"
        }
      }
    }
  }
}
